{"gtabs":[{"panes":[{"ptabs":[{"history":[{"dir":"/home/as/.cache/git","file":"credential","relpos":1,"ts":1730718645},{"dir":"/home/as/.cache/git/credential","file":"..","relpos":0,"ts":1730718645},{"dir":"/home/as/.cache/git","file":"..","relpos":0,"ts":1730718645},{"dir":"/home/as/.cache","file":"fontconfig","relpos":4,"ts":1730718645},{"dir":"/home/as/.cache/fontconfig","file":"..","relpos":0,"ts":1730718645},{"dir":"/home/as/.cache","file":"font-manager","relpos":3,"ts":1730718645},{"dir":"/home/as/.cache/font-manager","file":"..","relpos":0,"ts":1730718645},{"dir":"/home/as/.cache","file":"cliphist","relpos":2,"ts":1730718645},{"dir":"/home/as/.cache/cliphist","file":"..","relpos":0,"ts":1730718645},{"dir":"/home/as/.cache","file":"ImageMagick","relpos":1,"ts":1730718645},{"dir":"/home/as/.cache/ImageMagick","file":"..","relpos":0,"ts":1730718645},{"dir":"/home/as/.cache","file":"..","relpos":0,"ts":1730718645},{"dir":"/home/as","file":"..","relpos":0,"ts":1730718645},{"dir":"/home","file":"as","relpos":1,"ts":1730718645},{"dir":"/home/as/.config","file":"waybar","relpos":32,"ts":1730718651},{"dir":"/home/as/.config/waybar","file":"themes","relpos":1,"ts":1730718651},{"dir":"/home/as/.config/waybar/themes","file":"myset","relpos":1,"ts":1730718651},{"dir":"/home/as/.config/waybar/themes/myset","file":"style.css","relpos":6,"ts":1730718651},{"dir":"/home/as","file":".bash_profile","relpos":18,"ts":1730718651},{"dir":"/usr","file":"bin","relpos":1,"ts":1730718651},{"dir":"/usr/bin","file":"djpeg","relpos":20,"ts":1730718651},{"dir":"/home/as","file":".bash_profile","relpos":18,"ts":1730718651},{"dir":"/home/as/.config","file":"waybar","relpos":32,"ts":1730718651},{"dir":"/home/as/.config/waybar","file":"themes","relpos":1,"ts":1730718651},{"dir":"/home/as/.config/waybar/themes","file":"myset","relpos":1,"ts":1730718651},{"dir":"/home/as/.config/waybar/themes/myset","file":"style.css","relpos":6,"ts":1730718651},{"dir":"/home/as","file":".bash_profile","relpos":18,"ts":1730718651},{"dir":"/usr","file":"bin","relpos":1,"ts":1730718651},{"dir":"/usr/bin","file":"djpeg","relpos":20,"ts":1730718651},{"dir":"/home/as","file":".bash_profile","relpos":18,"ts":1730718651},{"dir":"/home/as/.config","file":"waybar","relpos":32,"ts":1730718651},{"dir":"/home/as/.config/waybar","file":"themes","relpos":1,"ts":1730718651},{"dir":"/home/as/.config/waybar/themes","file":"myset","relpos":1,"ts":1730718651},{"dir":"/home/as/.config/waybar/themes/myset","file":"style.css","relpos":6,"ts":1730718651},{"dir":"/home/as","file":".bash_profile","relpos":18,"ts":1730718651},{"dir":"/usr","file":"bin","relpos":1,"ts":1730718651},{"dir":"/usr/bin","file":"djpeg","relpos":20,"ts":1730718651},{"dir":"/home/as","file":".bash_profile","relpos":18,"ts":1730718651},{"dir":"/home/as/.config","file":"waybar","relpos":32,"ts":1730718651},{"dir":"/home/as/.config/waybar","file":"themes","relpos":1,"ts":1730718651},{"dir":"/home/as/.config/waybar/themes","file":"myset","relpos":1,"ts":1730718651},{"dir":"/home/as/.config/waybar/themes/myset","file":"style.css","relpos":6,"ts":1730718651},{"dir":"/home/as","file":".bash_profile","relpos":18,"ts":1730718651},{"dir":"/usr","file":"bin","relpos":1,"ts":1730718651},{"dir":"/usr/bin","file":"djpeg","relpos":20,"ts":1730718651},{"dir":"/home/as","file":".bash_profile","relpos":18,"ts":1730718651},{"dir":"/home/as/.config","file":"waybar","relpos":32,"ts":1730718651},{"dir":"/home/as/.config/waybar","file":"themes","relpos":1,"ts":1730718651},{"dir":"/home/as/.config/waybar/themes","file":"myset","relpos":1,"ts":1730718651},{"dir":"/home/as/.config/waybar/themes/myset","file":"style.css","relpos":6,"ts":1730718651},{"dir":"/home/as","file":".bash_profile","relpos":18,"ts":1730718651},{"dir":"/usr","file":"bin","relpos":1,"ts":1730718651},{"dir":"/usr/bin","file":"djpeg","relpos":20,"ts":1730718651},{"dir":"/home/as","file":".bash_profile","relpos":18,"ts":1730718651},{"dir":"/home/as/.config","file":"wlogout","relpos":34,"ts":1730718651},{"dir":"/home/as/.config/wlogout","file":"..","relpos":0,"ts":1730718760},{"dir":"/home/as/.config","file":"waybar","relpos":32,"ts":1730718760},{"dir":"/home/as/.config/waybar","file":"..","relpos":0,"ts":1730718760},{"dir":"/home/as/.config/wlogout","file":"..","relpos":0,"ts":1730718760},{"dir":"/home/as/.config","file":"waybar","relpos":32,"ts":1730718760},{"dir":"/home/as/.config/waybar","file":"..","relpos":0,"ts":1730718760},{"dir":"/home/as/.config/wlogout","file":"..","relpos":0,"ts":1730718760},{"dir":"/home/as/.config","file":"waybar","relpos":32,"ts":1730718760},{"dir":"/home/as/.config/waybar","file":"..","relpos":0,"ts":1730718760},{"dir":"/home/as/.config/wlogout","file":"..","relpos":0,"ts":1730718760},{"dir":"/home/as/.config","file":"waybar","relpos":32,"ts":1730718760},{"dir":"/home/as/.config/waybar","file":"..","relpos":0,"ts":1730718760},{"dir":"/home/as/.config/wlogout","file":"..","relpos":0,"ts":1730718760},{"dir":"/home/as/.config","file":"waybar","relpos":32,"ts":1730718760},{"dir":"/home/as/.config/waybar","file":"..","relpos":0,"ts":1730718760},{"dir":"/home/as/.config","file":"wlogout","relpos":34,"ts":1730719270},{"dir":"/home/as/.config/wlogout","file":"readme","relpos":4,"ts":1730719270},{"dir":"/home/as/.config","file":"wlogout","relpos":34,"ts":1730719270},{"dir":"/home/as/.config/wlogout","file":"..","relpos":0,"ts":1730719270},{"dir":"/home/as/.config","file":"wlogout","relpos":34,"ts":1730719270},{"dir":"/home/as/.config/wlogout","file":"..","relpos":0,"ts":1730719270},{"dir":"/home/as/.config","file":"wlogout","relpos":34,"ts":1730719270},{"dir":"/home/as/.config/wlogout","file":"readme","relpos":4,"ts":1730719270},{"dir":"/home/as/.config","file":"wlogout","relpos":34,"ts":1730719270},{"dir":"/home/as/.config/wlogout","file":"..","relpos":0,"ts":1730719270},{"dir":"/home/as/.config","file":"..","relpos":0,"ts":1730719420},{"dir":"/home/as","file":".cache","relpos":1,"ts":1730719420},{"dir":"/home/as/.cache","file":"wal","relpos":19,"ts":1730719420},{"dir":"/home/as/.cache/wal","file":"colors-wlogout.css","relpos":20,"ts":1730719420},{"dir":"/home/as/.config","file":"..","relpos":0,"ts":1730719420},{"dir":"/home/as","file":".cache","relpos":1,"ts":1730719420},{"dir":"/home/as/.cache","file":"wal","relpos":19,"ts":1730719420},{"dir":"/home/as/.cache/wal","file":"colors-wlogout.css","relpos":20,"ts":1730719420},{"dir":"/home/as/.config","file":"..","relpos":0,"ts":1730719420},{"dir":"/home/as","file":".cache","relpos":1,"ts":1730719420},{"dir":"/home/as/.cache","file":"wal","relpos":19,"ts":1730719420},{"dir":"/home/as/.cache/wal","file":"colors-wlogout.css","relpos":20,"ts":1730719420},{"dir":"/home/as/.config","file":"wlogout","relpos":34,"ts":1730720490},{"dir":"/home/as/.config/wlogout","file":"..","relpos":0,"ts":1730720490},{"dir":"/home/as/.config","file":"wlogout","relpos":34,"ts":1730720490},{"dir":"/home/as","file":".config","relpos":2,"ts":1730720490},{"dir":"/home/as/.config","file":"hypr","relpos":16,"ts":1730720490},{"dir":"/home/as/.config/hypr","file":"conf","relpos":1,"ts":1730720490},{"dir":"/home/as/.config/hypr/conf","file":"keybindings.conf","relpos":9,"ts":1730720490},{"dir":"/home/as/.config/wlogout","file":"..","relpos":0,"ts":1730720493}],"filters":{"invert":true,"dot":false,"manual":"","auto":""},"last-location":"/home/as/.config/wlogout","sorting":[2],"preview":false}]},{"ptabs":[{"history":[{"dir":"/home/as/Pictures","file":"..","relpos":0,"ts":1730715298},{"dir":"/home/as","file":".config","relpos":2,"ts":1730715298},{"dir":"/home/as/.config","file":"pulse","relpos":23,"ts":1730715298},{"dir":"/home/as/.local","file":"..","relpos":0,"ts":1730718645},{"dir":"/etc","file":"issue","relpos":4,"ts":1730718645},{"dir":"/usr","file":"..","relpos":0,"ts":1730718645},{"dir":"/home/as","file":".config","relpos":2,"ts":1730718645},{"dir":"/home/as/.config","file":"vifm","relpos":29,"ts":1730718645},{"dir":"/home/as/.local","file":"bin","relpos":1,"ts":1730718645},{"dir":"/home/as/.local/bin","file":"..","relpos":0,"ts":1730718645},{"dir":"/home/as/.local","file":"..","relpos":0,"ts":1730718645},{"dir":"/etc","file":"issue","relpos":4,"ts":1730718645},{"dir":"/usr","file":"..","relpos":0,"ts":1730718645},{"dir":"/home/as","file":".config","relpos":2,"ts":1730718645},{"dir":"/home/as/.config","file":"vifm","relpos":29,"ts":1730718645},{"dir":"/home/as/.local","file":"bin","relpos":1,"ts":1730718645},{"dir":"/home/as/.local/bin","file":"..","relpos":0,"ts":1730718645},{"dir":"/home/as/.local","file":"..","relpos":0,"ts":1730718645},{"dir":"/etc","file":"issue","relpos":4,"ts":1730718645},{"dir":"/usr","file":"..","relpos":0,"ts":1730718645},{"dir":"/home/as","file":".config","relpos":2,"ts":1730718645},{"dir":"/home/as/.config","file":"vifm","relpos":29,"ts":1730718645},{"dir":"/home/as/.local","file":"bin","relpos":1,"ts":1730718645},{"dir":"/home/as/.local/bin","file":"..","relpos":0,"ts":1730718645},{"dir":"/home/as/.local","file":"..","relpos":0,"ts":1730718645},{"dir":"/etc","file":"issue","relpos":4,"ts":1730718645},{"dir":"/usr","file":"..","relpos":0,"ts":1730718645},{"dir":"/home/as","file":".config","relpos":2,"ts":1730718645},{"dir":"/home/as/.config","file":"vifm","relpos":29,"ts":1730718645},{"dir":"/home/as/.local","file":"bin","relpos":1,"ts":1730718645},{"dir":"/home/as/.local/bin","file":"..","relpos":0,"ts":1730718645},{"dir":"/home/as/.local","file":"..","relpos":0,"ts":1730718645},{"dir":"/etc","file":"issue","relpos":4,"ts":1730718645},{"dir":"/usr","file":"..","relpos":0,"ts":1730718645},{"dir":"/home/as","file":".config","relpos":2,"ts":1730718645},{"dir":"/home/as/.config","file":"vifm","relpos":29,"ts":1730718645},{"dir":"/home/as/.local","file":"bin","relpos":1,"ts":1730718645},{"dir":"/home/as/.local/bin","file":"..","relpos":0,"ts":1730718645},{"dir":"/home/as/.local","file":"bin","relpos":1,"ts":1730718651},{"dir":"/home/as/.local/bin","file":"..","relpos":0,"ts":1730718651},{"dir":"/home/as/.local","file":"bin","relpos":1,"ts":1730718651},{"dir":"/home/as/.local/bin","file":"cliphist.sh","relpos":2,"ts":1730718651},{"dir":"/home/as/.local","file":"bin","relpos":1,"ts":1730718651},{"dir":"/home/as/.local/bin","file":"cliphist.sh","relpos":2,"ts":1730718651},{"dir":"/home/as/.local","file":"bin","relpos":1,"ts":1730718651},{"dir":"/home/as/.local/bin","file":"..","relpos":0,"ts":1730718651},{"dir":"/home/as/.local","file":"bin","relpos":1,"ts":1730718651},{"dir":"/home/as/.local/bin","file":"cliphist.sh","relpos":2,"ts":1730718651},{"dir":"/home/as/.local","file":"..","relpos":0,"ts":1730720263},{"dir":"/home/as","file":"Documents","relpos":9,"ts":1730720263},{"dir":"/home/as/Documents","file":"backup","relpos":1,"ts":1730720263},{"dir":"/home/as/Documents/backup","file":"..","relpos":0,"ts":1730720263},{"dir":"/home/as/Documents","file":"..","relpos":0,"ts":1730720263},{"dir":"/home/as","file":"hypr-void","relpos":14,"ts":1730720263},{"dir":"/home/as/hypr-void","file":".config","relpos":1,"ts":1730720263},{"dir":"/home/as/hypr-void/.config","file":"wlogout","relpos":21,"ts":1730720263},{"dir":"/home/as/hypr-void/.config/wlogout","file":"..","relpos":0,"ts":1730720263},{"dir":"/home/as/hypr-void/.config","file":"..","relpos":0,"ts":1730720263},{"dir":"/home/as/hypr-void","file":"..","relpos":0,"ts":1730720263},{"dir":"/home/as","file":"Documents","relpos":9,"ts":1730720263},{"dir":"/home/as/Documents","file":"backup","relpos":1,"ts":1730720263},{"dir":"/home/as/Documents/backup","file":"..","relpos":0,"ts":1730720263},{"dir":"/home/as/Documents","file":"..","relpos":0,"ts":1730720263},{"dir":"/home/as","file":"hypr-void","relpos":14,"ts":1730720263},{"dir":"/home/as/hypr-void","file":".config","relpos":1,"ts":1730720263},{"dir":"/home/as/hypr-void/.config","file":"xsettingsd","relpos":22,"ts":1730720263},{"dir":"/home/as/hypr-void/.config/xsettingsd","file":"..","relpos":0,"ts":1730720263},{"dir":"/home/as/hypr-void/.config","file":"wlogout","relpos":21,"ts":1730720263},{"dir":"/home/as/hypr-void/.config/wlogout","file":"..","relpos":0,"ts":1730720263},{"dir":"/home/as/hypr-void/.config","file":"..","relpos":0,"ts":1730720263},{"dir":"/home/as/hypr-void","file":"..","relpos":0,"ts":1730720263},{"dir":"/home/as","file":"Documents","relpos":9,"ts":1730720263},{"dir":"/home/as/Documents","file":"backup","relpos":1,"ts":1730720263},{"dir":"/home/as/Documents/backup","file":"layout","relpos":5,"ts":1730720263},{"dir":"/home/as/.local","file":"..","relpos":0,"ts":1730720263},{"dir":"/home/as","file":"Documents","relpos":9,"ts":1730720263},{"dir":"/home/as/Documents","file":"backup","relpos":1,"ts":1730720263},{"dir":"/home/as/Documents/backup","file":"..","relpos":0,"ts":1730720263},{"dir":"/home/as/Documents","file":"..","relpos":0,"ts":1730720263},{"dir":"/home/as","file":"hypr-void","relpos":14,"ts":1730720263},{"dir":"/home/as/hypr-void","file":".config","relpos":1,"ts":1730720263},{"dir":"/home/as/hypr-void/.config","file":"wlogout","relpos":21,"ts":1730720263},{"dir":"/home/as/hypr-void/.config/wlogout","file":"..","relpos":0,"ts":1730720263},{"dir":"/home/as/hypr-void/.config","file":"..","relpos":0,"ts":1730720263},{"dir":"/home/as/hypr-void","file":"..","relpos":0,"ts":1730720263},{"dir":"/home/as","file":"Documents","relpos":9,"ts":1730720263},{"dir":"/home/as/Documents","file":"backup","relpos":1,"ts":1730720263},{"dir":"/home/as/Documents/backup","file":"..","relpos":0,"ts":1730720263},{"dir":"/home/as/Documents","file":"..","relpos":0,"ts":1730720263},{"dir":"/home/as","file":"hypr-void","relpos":14,"ts":1730720263},{"dir":"/home/as/hypr-void","file":".config","relpos":1,"ts":1730720263},{"dir":"/home/as/hypr-void/.config","file":"xsettingsd","relpos":22,"ts":1730720263},{"dir":"/home/as/hypr-void/.config/xsettingsd","file":"..","relpos":0,"ts":1730720263},{"dir":"/home/as/hypr-void/.config","file":"wlogout","relpos":21,"ts":1730720263},{"dir":"/home/as/hypr-void/.config/wlogout","file":"..","relpos":0,"ts":1730720263},{"dir":"/home/as/hypr-void/.config","file":"..","relpos":0,"ts":1730720263},{"dir":"/home/as/hypr-void","file":"..","relpos":0,"ts":1730720263},{"dir":"/home/as","file":"Documents","relpos":9,"ts":1730720263},{"dir":"/home/as/Documents","file":"backup","relpos":1,"ts":1730720263},{"dir":"/home/as/Documents/backup","file":"layout","relpos":5,"ts":1730720263}],"filters":{"invert":true,"dot":false,"manual":"","auto":""},"last-location":"/home/as/Documents/backup","sorting":[2],"preview":false}]}],"active-pane":0,"preview":false,"splitter":{"pos":-1,"ratio":0.5,"orientation":"v","expanded":false}}],"trash":[{"trashed":"/home/as/.local/share/vifm/Trash/000__home_as__config_wallpapers_040946828_282_jpg_dark_None_None_1.1.0.json","original":"/home/as/.cache/wal/schemes/_home_as__config_wallpapers_040946828_282_jpg_dark_None_None_1.1.0.json"},{"trashed":"/home/as/.local/share/vifm/Trash/000__home_as__config_wallpapers_11_jpg_dark_None_None_1.1.0.json","original":"/home/as/.cache/wal/schemes/_home_as__config_wallpapers_11_jpg_dark_None_None_1.1.0.json"},{"trashed":"/home/as/.local/share/vifm/Trash/000__home_as__config_wallpapers_13_jpg_dark_None_None_1.1.0.json","original":"/home/as/.cache/wal/schemes/_home_as__config_wallpapers_13_jpg_dark_None_None_1.1.0.json"},{"trashed":"/home/as/.local/share/vifm/Trash/000__home_as__config_wallpapers_16_jpg_dark_None_None_1.1.0.json","original":"/home/as/.cache/wal/schemes/_home_as__config_wallpapers_16_jpg_dark_None_None_1.1.0.json"},{"trashed":"/home/as/.local/share/vifm/Trash/000__home_as__config_wallpapers_1920-x-1080-minimalist-wallpaper-eelnu7smtlkqces6_jpg_dark_None_None_1.1.0.json","original":"/home/as/.cache/wal/schemes/_home_as__config_wallpapers_1920-x-1080-minimalist-wallpaper-eelnu7smtlkqces6_jpg_dark_None_None_1.1.0.json"},{"trashed":"/home/as/.local/share/vifm/Trash/000__home_as__config_wallpapers_2062849_jpg_dark_None_None_1.1.0.json","original":"/home/as/.cache/wal/schemes/_home_as__config_wallpapers_2062849_jpg_dark_None_None_1.1.0.json"},{"trashed":"/home/as/.local/share/vifm/Trash/000__home_as__config_wallpapers_23800_jpg_dark_None_None_1.1.0.json","original":"/home/as/.cache/wal/schemes/_home_as__config_wallpapers_23800_jpg_dark_None_None_1.1.0.json"},{"trashed":"/home/as/.local/share/vifm/Trash/000__home_as__config_wallpapers_3360d042e7b473f72954789a27f83478_jpeg_dark_None_None_1.1.0.json","original":"/home/as/.cache/wal/schemes/_home_as__config_wallpapers_3360d042e7b473f72954789a27f83478_jpeg_dark_None_None_1.1.0.json"},{"trashed":"/home/as/.local/share/vifm/Trash/000__home_as__config_wallpapers_37720_jpg_dark_None_None_1.1.0.json","original":"/home/as/.cache/wal/schemes/_home_as__config_wallpapers_37720_jpg_dark_None_None_1.1.0.json"},{"trashed":"/home/as/.local/share/vifm/Trash/000__home_as__config_wallpapers_37855_jpg_dark_None_None_1.1.0.json","original":"/home/as/.cache/wal/schemes/_home_as__config_wallpapers_37855_jpg_dark_None_None_1.1.0.json"},{"trashed":"/home/as/.local/share/vifm/Trash/000__home_as__config_wallpapers_37990_jpg_dark_None_None_1.1.0.json","original":"/home/as/.cache/wal/schemes/_home_as__config_wallpapers_37990_jpg_dark_None_None_1.1.0.json"},{"trashed":"/home/as/.local/share/vifm/Trash/000__home_as__config_wallpapers_489323_jpg_dark_None_None_1.1.0.json","original":"/home/as/.cache/wal/schemes/_home_as__config_wallpapers_489323_jpg_dark_None_None_1.1.0.json"},{"trashed":"/home/as/.local/share/vifm/Trash/000__home_as__config_wallpapers_489353_jpg_dark_None_None_1.1.0.json","original":"/home/as/.cache/wal/schemes/_home_as__config_wallpapers_489353_jpg_dark_None_None_1.1.0.json"},{"trashed":"/home/as/.local/share/vifm/Trash/000__home_as__config_wallpapers_Bird_jpg_dark_None_None_1.1.0.json","original":"/home/as/.cache/wal/schemes/_home_as__config_wallpapers_Bird_jpg_dark_None_None_1.1.0.json"},{"trashed":"/home/as/.local/share/vifm/Trash/000__home_as__config_wallpapers_McLaren-F1_jpg_dark_None_None_1.1.0.json","original":"/home/as/.cache/wal/schemes/_home_as__config_wallpapers_McLaren-F1_jpg_dark_None_None_1.1.0.json"},{"trashed":"/home/as/.local/share/vifm/Trash/000__home_as__config_wallpapers_Mercedes-F1_jpg_dark_None_None_1.1.0.json","original":"/home/as/.cache/wal/schemes/_home_as__config_wallpapers_Mercedes-F1_jpg_dark_None_None_1.1.0.json"},{"trashed":"/home/as/.local/share/vifm/Trash/000__home_as__config_wallpapers_Rolls-Royce_jpg_dark_None_None_1.1.0.json","original":"/home/as/.cache/wal/schemes/_home_as__config_wallpapers_Rolls-Royce_jpg_dark_None_None_1.1.0.json"},{"trashed":"/home/as/.local/share/vifm/Trash/000__home_as__config_wallpapers_VDawg_jpg_dark_None_None_1.1.0.json","original":"/home/as/.cache/wal/schemes/_home_as__config_wallpapers_VDawg_jpg_dark_None_None_1.1.0.json"},{"trashed":"/home/as/.local/share/vifm/Trash/000__home_as__config_wallpapers_W7XnDl_jpg_dark_None_None_1.1.0.json","original":"/home/as/.cache/wal/schemes/_home_as__config_wallpapers_W7XnDl_jpg_dark_None_None_1.1.0.json"},{"trashed":"/home/as/.local/share/vifm/Trash/000__home_as__config_wallpapers_abyss_jpg_dark_None_None_1.1.0.json","original":"/home/as/.cache/wal/schemes/_home_as__config_wallpapers_abyss_jpg_dark_None_None_1.1.0.json"},{"trashed":"/home/as/.local/share/vifm/Trash/000__home_as__config_wallpapers_art-W7XnDl_jpg_dark_None_None_1.1.0.json","original":"/home/as/.cache/wal/schemes/_home_as__config_wallpapers_art-W7XnDl_jpg_dark_None_None_1.1.0.json"},{"trashed":"/home/as/.local/share/vifm/Trash/000__home_as__config_wallpapers_art-wallpaper-10_jpg_dark_None_None_1.1.0.json","original":"/home/as/.cache/wal/schemes/_home_as__config_wallpapers_art-wallpaper-10_jpg_dark_None_None_1.1.0.json"},{"trashed":"/home/as/.local/share/vifm/Trash/000__home_as__config_wallpapers_art-wallpapers-hd-2_jpg_dark_None_None_1.1.0.json","original":"/home/as/.cache/wal/schemes/_home_as__config_wallpapers_art-wallpapers-hd-2_jpg_dark_None_None_1.1.0.json"},{"trashed":"/home/as/.local/share/vifm/Trash/000__home_as__config_wallpapers_beach-prisma_jpg_dark_None_None_1.1.0.json","original":"/home/as/.cache/wal/schemes/_home_as__config_wallpapers_beach-prisma_jpg_dark_None_None_1.1.0.json"},{"trashed":"/home/as/.local/share/vifm/Trash/000__home_as__config_wallpapers_bird-1428583_jpg_dark_None_None_1.1.0.json","original":"/home/as/.cache/wal/schemes/_home_as__config_wallpapers_bird-1428583_jpg_dark_None_None_1.1.0.json"},{"trashed":"/home/as/.local/share/vifm/Trash/000__home_as__config_wallpapers_brembo_jpeg_dark_None_None_1.1.0.json","original":"/home/as/.cache/wal/schemes/_home_as__config_wallpapers_brembo_jpeg_dark_None_None_1.1.0.json"},{"trashed":"/home/as/.local/share/vifm/Trash/000__home_as__config_wallpapers_default_jpg_dark_None_None_1.1.0.json","original":"/home/as/.cache/wal/schemes/_home_as__config_wallpapers_default_jpg_dark_None_None_1.1.0.json"},{"trashed":"/home/as/.local/share/vifm/Trash/000__home_as__config_wallpapers_digital-circle_jpg_dark_None_None_1.1.0.json","original":"/home/as/.cache/wal/schemes/_home_as__config_wallpapers_digital-circle_jpg_dark_None_None_1.1.0.json"},{"trashed":"/home/as/.local/share/vifm/Trash/000__home_as__config_wallpapers_end_4_jpg_dark_None_None_1.1.0.json","original":"/home/as/.cache/wal/schemes/_home_as__config_wallpapers_end_4_jpg_dark_None_None_1.1.0.json"},{"trashed":"/home/as/.local/share/vifm/Trash/000__home_as__config_wallpapers_f1-legend_jpeg_dark_None_None_1.1.0.json","original":"/home/as/.cache/wal/schemes/_home_as__config_wallpapers_f1-legend_jpeg_dark_None_None_1.1.0.json"},{"trashed":"/home/as/.local/share/vifm/Trash/000__home_as__config_wallpapers_fall-leaf_jpg_dark_None_None_1.1.0.json","original":"/home/as/.cache/wal/schemes/_home_as__config_wallpapers_fall-leaf_jpg_dark_None_None_1.1.0.json"},{"trashed":"/home/as/.local/share/vifm/Trash/000__home_as__config_wallpapers_lights_jpg_dark_None_None_1.1.0.json","original":"/home/as/.cache/wal/schemes/_home_as__config_wallpapers_lights_jpg_dark_None_None_1.1.0.json"},{"trashed":"/home/as/.local/share/vifm/Trash/000__home_as__config_wallpapers_lofoten-sundown_jpg_dark_None_None_1.1.0.json","original":"/home/as/.cache/wal/schemes/_home_as__config_wallpapers_lofoten-sundown_jpg_dark_None_None_1.1.0.json"},{"trashed":"/home/as/.local/share/vifm/Trash/000__home_as__config_wallpapers_minimalist-mountains-green-4k-a3_jpg_dark_None_None_1.1.0.json","original":"/home/as/.cache/wal/schemes/_home_as__config_wallpapers_minimalist-mountains-green-4k-a3_jpg_dark_None_None_1.1.0.json"},{"trashed":"/home/as/.local/share/vifm/Trash/000__home_as__config_wallpapers_mjixd4eqw4q61_png_dark_None_None_1.1.0.json","original":"/home/as/.cache/wal/schemes/_home_as__config_wallpapers_mjixd4eqw4q61_png_dark_None_None_1.1.0.json"},{"trashed":"/home/as/.local/share/vifm/Trash/000__home_as__config_wallpapers_mountains-green_jpg_dark_None_None_1.1.0.json","original":"/home/as/.cache/wal/schemes/_home_as__config_wallpapers_mountains-green_jpg_dark_None_None_1.1.0.json"},{"trashed":"/home/as/.local/share/vifm/Trash/000__home_as__config_wallpapers_pitstop_png_dark_None_None_1.1.0.json","original":"/home/as/.cache/wal/schemes/_home_as__config_wallpapers_pitstop_png_dark_None_None_1.1.0.json"},{"trashed":"/home/as/.local/share/vifm/Trash/000__home_as__config_wallpapers_sea-water_jpg_dark_None_None_1.1.0.json","original":"/home/as/.cache/wal/schemes/_home_as__config_wallpapers_sea-water_jpg_dark_None_None_1.1.0.json"},{"trashed":"/home/as/.local/share/vifm/Trash/000__home_as__config_wallpapers_senna_jpeg_dark_None_None_1.1.0.json","original":"/home/as/.cache/wal/schemes/_home_as__config_wallpapers_senna_jpeg_dark_None_None_1.1.0.json"},{"trashed":"/home/as/.local/share/vifm/Trash/000__home_as__config_wallpapers_sundown-over-sea_jpg_dark_None_None_1.1.0.json","original":"/home/as/.cache/wal/schemes/_home_as__config_wallpapers_sundown-over-sea_jpg_dark_None_None_1.1.0.json"},{"trashed":"/home/as/.local/share/vifm/Trash/000__home_as__config_wallpapers_telescope_jpg_dark_None_None_1.1.0.json","original":"/home/as/.cache/wal/schemes/_home_as__config_wallpapers_telescope_jpg_dark_None_None_1.1.0.json"},{"trashed":"/home/as/.local/share/vifm/Trash/000__home_as__config_wallpapers_tokyo-57_jpg_dark_None_None_1.1.0.json","original":"/home/as/.cache/wal/schemes/_home_as__config_wallpapers_tokyo-57_jpg_dark_None_None_1.1.0.json"},{"trashed":"/home/as/.local/share/vifm/Trash/000__home_as__config_wallpapers_tokyo-city-minimalist-4k-57_jpg_dark_None_None_1.1.0.json","original":"/home/as/.cache/wal/schemes/_home_as__config_wallpapers_tokyo-city-minimalist-4k-57_jpg_dark_None_None_1.1.0.json"},{"trashed":"/home/as/.local/share/vifm/Trash/000__home_as__config_wallpapers_void-101_jpg_dark_None_None_1.1.0.json","original":"/home/as/.cache/wal/schemes/_home_as__config_wallpapers_void-101_jpg_dark_None_None_1.1.0.json"},{"trashed":"/home/as/.local/share/vifm/Trash/000__home_as__config_wallpapers_void-102_jpg_dark_None_None_1.1.0.json","original":"/home/as/.cache/wal/schemes/_home_as__config_wallpapers_void-102_jpg_dark_None_None_1.1.0.json"},{"trashed":"/home/as/.local/share/vifm/Trash/000__home_as__config_wallpapers_void-102_png_dark_None_None_1.1.0.json","original":"/home/as/.cache/wal/schemes/_home_as__config_wallpapers_void-102_png_dark_None_None_1.1.0.json"},{"trashed":"/home/as/.local/share/vifm/Trash/000__home_as__config_wallpapers_void-103_jpg_dark_None_None_1.1.0.json","original":"/home/as/.cache/wal/schemes/_home_as__config_wallpapers_void-103_jpg_dark_None_None_1.1.0.json"},{"trashed":"/home/as/.local/share/vifm/Trash/000__home_as__config_wallpapers_void-106_png_dark_None_None_1.1.0.json","original":"/home/as/.cache/wal/schemes/_home_as__config_wallpapers_void-106_png_dark_None_None_1.1.0.json"},{"trashed":"/home/as/.local/share/vifm/Trash/000__home_as__config_wallpapers_void-122_png_dark_None_None_1.1.0.json","original":"/home/as/.cache/wal/schemes/_home_as__config_wallpapers_void-122_png_dark_None_None_1.1.0.json"},{"trashed":"/home/as/.local/share/vifm/Trash/000__home_as__config_wallpapers_void-1_jpeg_dark_None_None_1.1.0.json","original":"/home/as/.cache/wal/schemes/_home_as__config_wallpapers_void-1_jpeg_dark_None_None_1.1.0.json"},{"trashed":"/home/as/.local/share/vifm/Trash/000__home_as__config_wallpapers_void-26_png_dark_None_None_1.1.0.json","original":"/home/as/.cache/wal/schemes/_home_as__config_wallpapers_void-26_png_dark_None_None_1.1.0.json"},{"trashed":"/home/as/.local/share/vifm/Trash/000__home_as__config_wallpapers_void-2_png_dark_None_None_1.1.0.json","original":"/home/as/.cache/wal/schemes/_home_as__config_wallpapers_void-2_png_dark_None_None_1.1.0.json"},{"trashed":"/home/as/.local/share/vifm/Trash/000__home_as__config_wallpapers_void-5_jpg_dark_None_None_1.1.0.json","original":"/home/as/.cache/wal/schemes/_home_as__config_wallpapers_void-5_jpg_dark_None_None_1.1.0.json"},{"trashed":"/home/as/.local/share/vifm/Trash/000__home_as__config_wallpapers_void-61_png_dark_None_None_1.1.0.json","original":"/home/as/.cache/wal/schemes/_home_as__config_wallpapers_void-61_png_dark_None_None_1.1.0.json"},{"trashed":"/home/as/.local/share/vifm/Trash/000__home_as__config_wallpapers_void-62_png_dark_None_None_1.1.0.json","original":"/home/as/.cache/wal/schemes/_home_as__config_wallpapers_void-62_png_dark_None_None_1.1.0.json"},{"trashed":"/home/as/.local/share/vifm/Trash/000__home_as__config_wallpapers_void-8_jpg_dark_None_None_1.1.0.json","original":"/home/as/.cache/wal/schemes/_home_as__config_wallpapers_void-8_jpg_dark_None_None_1.1.0.json"},{"trashed":"/home/as/.local/share/vifm/Trash/000__home_as__config_wallpapers_void-dota_jpeg_dark_None_None_1.1.0.json","original":"/home/as/.cache/wal/schemes/_home_as__config_wallpapers_void-dota_jpeg_dark_None_None_1.1.0.json"},{"trashed":"/home/as/.local/share/vifm/Trash/000__home_as__config_wallpapers_void-jump_jpeg_dark_None_None_1.1.0.json","original":"/home/as/.cache/wal/schemes/_home_as__config_wallpapers_void-jump_jpeg_dark_None_None_1.1.0.json"},{"trashed":"/home/as/.local/share/vifm/Trash/000__home_as__config_wallpapers_void-world_jpeg_dark_None_None_1.1.0.json","original":"/home/as/.cache/wal/schemes/_home_as__config_wallpapers_void-world_jpeg_dark_None_None_1.1.0.json"},{"trashed":"/home/as/.local/share/vifm/Trash/000__home_as__config_wallpapers_wallhaven3_jpg_dark_None_None_1.1.0.json","original":"/home/as/.cache/wal/schemes/_home_as__config_wallpapers_wallhaven3_jpg_dark_None_None_1.1.0.json"},{"trashed":"/home/as/.local/share/vifm/Trash/000__home_as__config_wallpapers_williams-fw33_jpg_dark_None_None_1.1.0.json","original":"/home/as/.cache/wal/schemes/_home_as__config_wallpapers_williams-fw33_jpg_dark_None_None_1.1.0.json"},{"trashed":"/home/as/.local/share/vifm/Trash/000__home_as__config_wallpapers_windows-11_jpg_dark_None_None_1.1.0.json","original":"/home/as/.cache/wal/schemes/_home_as__config_wallpapers_windows-11_jpg_dark_None_None_1.1.0.json"},{"trashed":"/home/as/.local/share/vifm/Trash/001_scripts","original":"/home/as/.config/scripts"},{"trashed":"/home/as/.local/share/vifm/Trash/000_cleanup.sh","original":"/home/as/.config/scripts/cleanup.sh"},{"trashed":"/home/as/.local/share/vifm/Trash/000_cliphist.sh","original":"/home/as/.config/scripts/cliphist.sh"},{"trashed":"/home/as/.local/share/vifm/Trash/000_fuzzel.sh","original":"/home/as/.config/scripts/fuzzel.sh"},{"trashed":"/home/as/.local/share/vifm/Trash/000_installupdates.sh","original":"/home/as/.config/scripts/installupdates.sh"},{"trashed":"/home/as/.local/share/vifm/Trash/000_keybindings.sh","original":"/home/as/.config/scripts/keybindings.sh"},{"trashed":"/home/as/.local/share/vifm/Trash/000_mirrorlist.sh","original":"/home/as/.config/scripts/mirrorlist.sh"},{"trashed":"/home/as/.local/share/vifm/Trash/000_mpv.sh","original":"/home/as/.config/scripts/mpv.sh"},{"trashed":"/home/as/.local/share/vifm/Trash/000_pipewire.sh","original":"/home/as/.config/scripts/pipewire.sh"},{"trashed":"/home/as/.local/share/vifm/Trash/000_screenshot.sh","original":"/home/as/.config/scripts/screenshot.sh"},{"trashed":"/home/as/.local/share/vifm/Trash/000_script.sh","original":"/home/as/.config/scripts/script.sh"},{"trashed":"/home/as/.local/share/vifm/Trash/000_toggleallfloat.sh","original":"/home/as/.config/scripts/toggleallfloat.sh"},{"trashed":"/home/as/.local/share/vifm/Trash/000_updates.sh","original":"/home/as/.config/scripts/updates.sh"},{"trashed":"/home/as/.local/share/vifm/Trash/000_xdg.sh","original":"/home/as/.config/scripts/xdg.sh"},{"trashed":"/home/as/.local/share/vifm/Trash/000_McLaren-F1.jpg","original":"/home/as/.config/wallpapers/McLaren-F1.jpg"},{"trashed":"/home/as/.local/share/vifm/Trash/000_Rolls-Royce.jpg","original":"/home/as/.config/wallpapers/Rolls-Royce.jpg"},{"trashed":"/home/as/.local/share/vifm/Trash/000_williams-fw33.jpg","original":"/home/as/.config/wallpapers/williams-fw33.jpg"},{"trashed":"/home/as/.local/share/vifm/Trash/000_windows-11.jpg","original":"/home/as/.config/wallpapers/windows-11.jpg"},{"trashed":"/home/as/.local/share/vifm/Trash/000_themeswitcher.sh","original":"/home/as/.config/waybar/themeswitcher.sh"},{"trashed":"/home/as/.local/share/vifm/Trash/000_weather.sh","original":"/home/as/.config/waybar/weather.sh"},{"trashed":"/home/as/.local/share/vifm/Trash/000_README.txt","original":"/home/as/.config/wlogout/README.txt"},{"trashed":"/home/as/.local/share/vifm/Trash/000_.profile","original":"/home/as/.profile"},{"trashed":"/home/as/.local/share/vifm/Trash/000_2024-10-19 13-50-57.mp4","original":"/home/as/2024-10-19 13-50-57.mp4"},{"trashed":"/home/as/.local/share/vifm/Trash/000_light_hyprland.odt","original":"/home/as/Documents/light_hyprland.odt"},{"trashed":"/home/as/.local/share/vifm/Trash/000_.Xresources","original":"/home/as/Downloads/.Xresources"},{"trashed":"/home/as/.local/share/vifm/Trash/000_.bash_profile","original":"/home/as/Downloads/.bash_profile"},{"trashed":"/home/as/.local/share/vifm/Trash/000_.bashrc","original":"/home/as/Downloads/.bashrc"},{"trashed":"/home/as/.local/share/vifm/Trash/000_.config","original":"/home/as/Downloads/.config"},{"trashed":"/home/as/.local/share/vifm/Trash/000_.gtkrc-2.0","original":"/home/as/Downloads/.gtkrc-2.0"},{"trashed":"/home/as/.local/share/vifm/Trash/000_.local","original":"/home/as/Downloads/.local"},{"trashed":"/home/as/.local/share/vifm/Trash/000_.my_aliases","original":"/home/as/Downloads/.my_aliases"},{"trashed":"/home/as/.local/share/vifm/Trash/000_.vim","original":"/home/as/Downloads/.vim"},{"trashed":"/home/as/.local/share/vifm/Trash/000_.vimrc","original":"/home/as/Downloads/.vimrc"},{"trashed":"/home/as/.local/share/vifm/Trash/000_.~lock.O gruppah po EB.docx#","original":"/home/as/Downloads/.~lock.O gruppah po EB.docx#"},{"trashed":"/home/as/.local/share/vifm/Trash/000_O gruppah po EB.docx","original":"/home/as/Downloads/O gruppah po EB.docx"},{"trashed":"/home/as/.local/share/vifm/Trash/000_README.md","original":"/home/as/Downloads/README.md"},{"trashed":"/home/as/.local/share/vifm/Trash/000_О фишинговых атаках.pdf","original":"/home/as/Downloads/Telegram Desktop/О фишинговых атаках.pdf"},{"trashed":"/home/as/.local/share/vifm/Trash/000_hypr-void","original":"/home/as/Downloads/hypr-void"},{"trashed":"/home/as/.local/share/vifm/Trash/000_issue","original":"/home/as/Downloads/issue"},{"trashed":"/home/as/.local/share/vifm/Trash/000_ОТЧЁТ нач.смены 01.11.24 (8-20).xls","original":"/home/as/Downloads/ОТЧЁТ нач.смены 01.11.24 (8-20).xls"},{"trashed":"/home/as/.local/share/vifm/Trash/000_mpv-shot0001.jpg","original":"/home/as/Pictures/screenshots/mpv-shot0001.jpg"},{"trashed":"/home/as/.local/share/vifm/Trash/000_mpv-shot0002.jpg","original":"/home/as/Pictures/screenshots/mpv-shot0002.jpg"},{"trashed":"/home/as/.local/share/vifm/Trash/000_mpv-shot0003.jpg","original":"/home/as/Pictures/screenshots/mpv-shot0003.jpg"},{"trashed":"/home/as/.local/share/vifm/Trash/000_screenshot_13102024_154148.jpg","original":"/home/as/Pictures/screenshots/screenshot_13102024_154148.jpg"},{"trashed":"/home/as/.local/share/vifm/Trash/000_screenshot_13102024_191954.jpg","original":"/home/as/Pictures/screenshots/screenshot_13102024_191954.jpg"},{"trashed":"/home/as/.local/share/vifm/Trash/000_screenshot_13102024_202506.jpg","original":"/home/as/Pictures/screenshots/screenshot_13102024_202506.jpg"},{"trashed":"/home/as/.local/share/vifm/Trash/000_screenshot_15102024_195325.jpg","original":"/home/as/Pictures/screenshots/screenshot_15102024_195325.jpg"},{"trashed":"/home/as/.local/share/vifm/Trash/000_screenshot_16102024_202450.jpg","original":"/home/as/Pictures/screenshots/screenshot_16102024_202450.jpg"},{"trashed":"/home/as/.local/share/vifm/Trash/000_scripts","original":"/home/as/hypr-void/.config/scripts"},{"trashed":"/home/as/.local/share/vifm/Trash/000_wallpapers","original":"/home/as/hypr-void/.config/wallpapers"},{"trashed":"/home/as/.local/share/vifm/Trash/000_waybar","original":"/home/as/hypr-void/.config/waybar"},{"trashed":"/home/as/.local/share/vifm/Trash/001_README.md","original":"/home/as/hypr-void/README.md"}],"marks":{"C":{"dir":"/home/as/.vifm/","file":"..","ts":1719253225},"H":{"dir":"/home/as/","file":"..","ts":1719053931},"M":{"dir":"/run/media/as/","file":"..","ts":1719063080},"P":{"dir":"/home/as/.config/wallpapers/","file":"..","ts":1728065134},"R":{"dir":"/","file":"..","ts":1719061620},"b":{"dir":"/home/as/.local/bin/","file":"..","ts":1729196711},"c":{"dir":"/home/as/.config/","file":"..","ts":1730718676},"d":{"dir":"/home/as/Downloads/","file":"..","ts":1729349603},"e":{"dir":"/etc","file":"..","ts":1730715298},"h":{"dir":"/home/as/","file":"..","ts":1729340713},"k":{"dir":"/home/as/.config/hypr/effects","file":"..","ts":1728334445},"l":{"dir":"/home/as/.local/","file":"..","ts":1730715298},"m":{"dir":"/run/media/as/","file":"..","ts":1730715298},"p":{"dir":"/home/as/Pictures/","file":"..","ts":1719061620},"r":{"dir":"/","file":"..","ts":1730715298},"s":{"dir":"/home/as/Pictures/screenshots","file":"..","ts":1730715298},"u":{"dir":"/usr","file":"..","ts":1730715298},"v":{"dir":"/home/as/Video/","file":"..","ts":1730715298},"w":{"dir":"/home/as/.config/wallpapers/","file":"..","ts":1730715298},"z":{"dir":"/home/as/.vifm","file":"..","ts":1719053931}},"bmarks":{},"cmd-hist":[{"text":"mkdir .config","ts":1719056997},{"text":"mkdir Downloads","ts":1719057646},{"text":"mkdir Music","ts":1719057646},{"text":"mkdir .local","ts":1719057646},{"text":"mkdir ~/.backup","ts":1719083575},{"text":"mkdir .backup","ts":1719083575},{"text":"zip","ts":1719092068},{"text":"unmap","ts":1719092068},{"text":"mkdir -p $HOME/.local/share/gtksourceview-3.0/styles","ts":1719263891},{"text":"mkdir gtksourceview-3.0/styles","ts":1719263891},{"text":"mkdir gtksourceview-3.0","ts":1719263891},{"text":"mkdir styles","ts":1719263891},{"text":"mkdir icons","ts":1719382929},{"text":"mkcd","ts":1719522321},{"text":"mkcd scripts","ts":1719522321},{"text":"mkdir","ts":1719522321},{"text":"mkdir script-opts","ts":1719522321},{"text":"mkdir scripts","ts":1719522321},{"text":"filextype","ts":1719730389},{"text":"dirs","ts":1719730389},{"text":"df","ts":1719730389},{"text":"hideui","ts":1719730389},{"text":"touch mypallete.rasi","ts":1720040653},{"text":"mkdir Hurmit","ts":1720125062},{"text":"mkdir Monofur","ts":1720125062},{"text":"mkdir OpenDyslexic","ts":1720125062},{"text":"touch MyTheme.rasi","ts":1720250773},{"text":"restore","ts":1720299543},{"text":"mkdir old","ts":1722194238},{"text":" touch hyprland-void.conf","ts":1726607897},{"text":"mkdir service","ts":1726936832},{"text":"extract","ts":1726941689},{"text":"mkdir Pictures","ts":1726985039},{"text":"mkdir Documents","ts":1726991359},{"text":"mkdir Video","ts":1726991359},{"text":"touch dracula.ini","ts":1727124415},{"text":"touch frappe.ini","ts":1727124415},{"text":"touch macchiato.ini","ts":1727124415},{"text":"touch end4.ini","ts":1727124415},{"text":"touch fblue.ini","ts":1727124415},{"text":"touch ludovic.ini","ts":1727124415},{"text":"mkdir themes","ts":1727124419},{"text":"touch latte.ini","ts":1727124419},{"text":"touch fuzzel.ini","ts":1727199601},{"text":"touch cursor.conf","ts":1727286938},{"text":"touch xbps.sh","ts":1727298453},{"text":"touch wall.sh","ts":1727452572},{"text":"e","ts":1727517283},{"text":"touch w3mpreview.sh","ts":1727901970},{"text":"mkdir git","ts":1727989912},{"text":"split","ts":1728067726},{"text":"mkdir effects","ts":1728335245},{"text":"mkdir wallpaper","ts":1728335245},{"text":"mkdir qt5ct","ts":1728581969},{"text":"mkdir colors","ts":1728581969},{"text":"mkdir colorschemes","ts":1728756689},{"text":"Q","ts":1728816733},{"text":"touch dmenu.sh","ts":1728942602},{"text":"touch luke.vifm","ts":1729198508},{"text":"media list","ts":1729341400},{"text":"mkdir ~/mnt","ts":1729350097},{"text":"s","ts":1729350097},{"text":"mkdir mnt","ts":1729350525},{"text":"mkdir google","ts":1729350525},{"text":"media","ts":1729424784},{"text":"mount","ts":1730014172},{"text":"touch weather.sh","ts":1730045714},{"text":"empty","ts":1730399476},{"text":"w","ts":1730703915},{"text":"reload","ts":1730715298},{"text":"touch readme","ts":1730720263},{"text":"q","ts":1730720263}],"prompt-hist":[{"text":"Palenight.rasi","ts":1720299543},{"text":"Solarized.rasi","ts":1720299543},{"text":"ephjcajbkgplkjmelpglennepbpmdpjg","ts":1721330120},{"text":"ff2mpv.json","ts":1721330137},{"text":"rtheme.sh","ts":1721503240},{"text":"qtheme.sh","ts":1721503240},{"text":"qtheme","ts":1721503240},{"text":"qtheme.json","ts":1721503240},{"text":"MyLight.rasi","ts":1721673836},{"text":"MyBlack.rasi","ts":1722105495},{"text":"merge","ts":1722194233},{"text":"config_theme","ts":1722194233},{"text":"config_theme.rasi","ts":1722194233},{"text":"Gruvbox","ts":1722194233},{"text":"split_img.sh","ts":1722194238},{"text":"merge_img.sh","ts":1722194238},{"text":"convert_img.sh","ts":1722194238},{"text":"convert-to-jpg.sh","ts":1722194238},{"text":"m-conv.sh","ts":1722194238},{"text":"archive","ts":1722194238},{"text":"scr.sh","ts":1722200980},{"text":"script.rasi","ts":1722200983},{"text":"script.sh","ts":1722275301},{"text":"ext","ts":1722283790},{"text":"extract.sh","ts":1722283790},{"text":"pipewire.desktop","ts":1727004086},{"text":"lockscreen.png","ts":1727037399},{"text":"brown.ini","ts":1727124415},{"text":"colorvoid.ini","ts":1727124415},{"text":"gvoid.ini","ts":1727124415},{"text":"fuzzel","ts":1727124419},{"text":"fuzzell.ini","ts":1727199601},{"text":"fuzzel.i","ts":1727199601},{"text":"fuzzel.ini","ts":1727199601},{"text":"xbpspkg.sh","ts":1727460622},{"text":"hyprland","ts":1727643504},{"text":"merge_290924_180617.zip","ts":1727643504},{"text":"merge_290924_180617.zz","ts":1727643504},{"text":"merge_290924_180617.png","ts":1727643504},{"text":"hyprland.tar","ts":1727643504},{"text":"hyprland.zip","ts":1727643504},{"text":"6.jpg","ts":1727812861},{"text":"void-9093.jpg","ts":1727812861},{"text":"abyss.jpg","ts":1727812861},{"text":"wallhaven.png","ts":1727812861},{"text":"vifmimg","ts":1727988067},{"text":"2023-12-31 18-35-26.mkv","ts":1728067726},{"text":"blur1","ts":1728335245},{"text":"blackwhite","ts":1728335245},{"text":"blackwhite-blur","ts":1728335245},{"text":"blackwhite-brightness40","ts":1728335245},{"text":"blackwhite-brightness60","ts":1728335245},{"text":"blackwhite-brightness80","ts":1728335245},{"text":"backup","ts":1728580391},{"text":"assets/no-events.svg","ts":1728669146},{"text":"metacity-theme-2.xml","ts":1728669146},{"text":"/home/as/.local/share/pipx/venvs/waypaper/bin/waypaper","ts":1728669146},{"text":"wall_v.jpg","ts":1728677208},{"text":"void-os.jpg","ts":1728677208},{"text":"void-minimalism.jpg","ts":1728677208},{"text":"11.jpg","ts":1728729388},{"text":"default.jpg","ts":1728729388},{"text":"v-8.jpg","ts":1728729388},{"text":"void-5.jpg","ts":1728729388},{"text":"void-8.jpg","ts":1728729388},{"text":"clouds.jpg","ts":1728729388},{"text":"void-13.jpg","ts":1728729388},{"text":"texture-world.jpg","ts":1728729388},{"text":"void-1.jpeg","ts":1728729388},{"text":"void-2.png","ts":1728729388},{"text":"tokyo-57.jpg","ts":1728729388},{"text":"void-1.jpg","ts":1728729388},{"text":"void-101.jpg","ts":1728729388},{"text":"void-102.png","ts":1728729388},{"text":"mountains-green.jpg","ts":1728729388},{"text":"void-logo.svg","ts":1728729388},{"text":"art-W7XnDl.jpg","ts":1728729388},{"text":"paper.micro","ts":1728756689},{"text":"paper-tc.micro","ts":1728756689},{"text":"patch.txt","ts":1728818780},{"text":"arcwaita.conf","ts":1728842315},{"text":"arc.conf","ts":1728842315},{"text":"Plume-Light.conf","ts":1728842315},{"text":"Plume-Dark.conf","ts":1728842315},{"text":"Arc-Light.conf","ts":1728842315},{"text":"Gruvbox-Dark.conf","ts":1728842315},{"text":"arc_light.conf","ts":1728842315},{"text":"latte.conf","ts":1728842315},{"text":"plume_light.conf","ts":1728842315},{"text":"plume_dark.conf","ts":1728842315},{"text":"gruvbox.conf","ts":1728842315},{"text":"arc-light.conf","ts":1728842315},{"text":"plume-dark.conf","ts":1728842315},{"text":"plume-light.conf","ts":1728842315},{"text":"screenshot_13102024_202506.png","ts":1728844295},{"text":"fuzzel.sh","ts":1729022259},{"text":"appmenu.sh","ts":1729022259},{"text":"phinger-cursors-variants.tar.bz2","ts":1729283979},{"text":"O gruppah po EB.docx","ts":1730485889},{"text":".profile","ts":1730707555}],"regs":{"\"":["/home/as/Documents/backup/layout"]},"dir-stack":[],"use-term-multiplexer":false}